Workbook

Sheet README
A1: WISDOM SCHOOLS – PROFESSIONAL BUDGET PLANNING WORKBOOK
A3: Purpose
A4: This workbook supports branch budget preparation, cash-flow forecasting, budget control, and structured import into the Wisdom Schools CodeIgniter 4 system.
A7: HOW TO USE
A8: 1. Complete organization, branch, year, dates, currency, and approval settings on SETUP.
A9: 2. Enter assumptions and planned amounts on BUDGET_PLAN. Blue-font cells are user inputs; black-font cells are formulas.
A10: 3. Choose a calculation mode: Monthly, Unit-based, or Manual Annual.
A11: 4. Review monthly and term-level liquidity on CASH_FLOW.
A12: 5. Review management KPIs, section totals, and charts on BUDGET_SUMMARY.
A13: 6. Use IMPORT_TEMPLATE as the clean, system-ready structure for upload into School Settings.
A14: 7. Do not delete formula columns or total rows. Add extra categories only in unused lines or through the application template manager.
A17: COLOR LEGEND
A18: Blue font / yellow fill | B18: User-entered assumptions and amounts
A19: Black font | B19: Formulas and calculated results
A20: Green font | B20: Links from another worksheet
A21: Orange fill | B21: Review or caution item
A22: Light red fill | B22: Error, missing data, or budget breach
A23: Purple fill | B23: Control or workflow setting
A26: CONTROL NOTES
A27: Amounts are expressed in the currency selected on SETUP.
A28: Zeros display as dashes; negative values display in red parentheses.
A29: Budget availability = approved/revised budget − commitments − paid actuals.
A30: AI suggestions, when used by the application, must remain advisory and require human confirmation.

Sheet SETUP
A1: BUDGET CONTROL & ORGANIZATION SETUP
A3: ORGANIZATION AND BUDGET PERIOD
A4: Setting | B4: Value | C4: Guidance
A5: Organization Name | B5: Wisdom Schools Ltd | C5: Official legal or operating name
A6: Branch | B6: Musanze | C6: Select one of the 15 branches
A7: Branch Code | B7: MUS | C7: Used in request numbering
A8: Budget Year | B8: 2027 | C8: Planning year
A9: Budget Period | B9: Annual | C9: Annual, termly, monthly, or quarterly
A10: Start Date | B10: 2027-01-01 | C10: Budget start date
A11: End Date | B11: 2027-12-31 | C11: Budget end date
A12: Currency | B12: RWF | C12: Workbook reporting currency
A13: Prepared By | C13: Name of School Accountant
A14: Headteacher | C14: Approving Headteacher
A15: Budget Manager | C15: Budget availability reviewer
A16: Deputy Director of Finance | C16: Final approver
A17: Version | B17: 1.0 | C17: Budget version
A18: Budget Status | B18: Draft | C18: Workflow status
A19: Headteacher Approval Mode | B19: Evidence-only Approval | C19: System approval or signed evidence
A22: PLANNING ASSUMPTIONS
A23: Assumption | B23: Value | C23: Unit | D23: Notes
A24: Expected Enrollment | B24: 0 | C24: Students
A25: Tuition Increase | B25: 0 | C25: %
A26: Food Cost Inflation | B26: 0 | C26: %
A27: General Inflation | B27: 0 | C27: %
A28: Salary Increase | B28: 0 | C28: %
A29: Contingency Rate | B29: 0.03 | C29: %
A30: Minimum Cash Buffer | B30: 0 | C30: RWF
A31: Budget Utilization Alert | B31: 0.8 | C31: %
A32: Critical Utilization Alert | B32: 0.95 | C32: %
A35: APPROVAL ROUTING
A36: Step | B36: Role | C36: Responsibility | D36: SLA (days) | E36: Active | F36: Notes
A37: 1 | B37: School Accountant | C37: Prepare and submit | D37: 2 | E37: Yes
A38: 2 | B38: Headteacher | C38: Approve in system or provide signed evidence | D38: 2 | E38: Yes
A39: 3 | B39: Procurement Manager | C39: Verify procurement compliance | D39: 2 | E39: Yes
A40: 4 | B40: Budget Manager | C40: Confirm budget availability and commitment | D40: 2 | E40: Yes
A41: 5 | B41: Deputy Director of Finance | C41: Final approval and payment authorization | D41: 2 | E41: Yes
A42: 6 | B42: Finance / Payment Officer | C42: Process payment | D42: 2 | E42: Yes
A43: 7 | B43: School Accountant | C43: Confirm receipt and file documents | D43: 2 | E43: Yes

Sheet BUDGET_PLAN
A1: SMART BUDGET PREPARATION FORM
A3: Branch | B3: =SETUP!B6 -> Musanze | D3: Budget Year | E3: =SETUP!B8 -> 2027 | G3: Period | H3: =SETUP!B9 -> Annual | J3: Currency | K3: =SETUP!B12 -> RWF | M3: Status | N3: =SETUP!B18 -> Draft
A5: Line ID | B5: Section | C5: Category | D5: Subcategory / Description | E5: Account Code | F5: Calculation Mode | G5: Quantity | H5: Unit | I5: Unit Cost | J5: Frequency | K5: Jan | L5: Feb | M5: Mar | N5: Apr | O5: May | P5: Jun | Q5: Jul | R5: Aug | S5: Sep | T5: Oct | U5: Nov | V5: Dec | W5: Term 1 | X5: Term 2 | Y5: Term 3 | Z5: Annual Budget | AA5: Previous Budget | AB5: Variance | AC5: Priority | AD5: Funding Source | AE5: Assumptions / Notes
A6: BL-001 | B6: INCOME | C6: School Fees | F6: Monthly | G6: 0 | H6: Other | I6: 0 | J6: 1 | K6: 0 | L6: 0 | M6: 0 | N6: 0 | O6: 0 | P6: 0 | Q6: 0 | R6: 0 | S6: 0 | T6: 0 | U6: 0 | V6: 0 | W6: =SUM(K6:N6) -> 0 | X6: =SUM(O6:R6) -> 0 | Y6: =SUM(S6:V6) -> 0 | Z6: =IF(F6="Monthly",SUM(K6:V6),IF(F6="Unit-based",G6*I6*J6,IF(F6="Manual Annual",SUM(K6:V6),0))) -> 0 | AA6: 0 | AB6: =IFERROR((Z6-AA6)/AA6,0) -> 0 | AC6: Medium | AD6: School Fees
A7: BL-002 | B7: INCOME | C7: Lunch | F7: Monthly | G7: 0 | H7: Other | I7: 0 | J7: 1 | K7: 0 | L7: 0 | M7: 0 | N7: 0 | O7: 0 | P7: 0 | Q7: 0 | R7: 0 | S7: 0 | T7: 0 | U7: 0 | V7: 0 | W7: =SUM(K7:N7) -> 0 | X7: =SUM(O7:R7) -> 0 | Y7: =SUM(S7:V7) -> 0 | Z7: =IF(F7="Monthly",SUM(K7:V7),IF(F7="Unit-based",G7*I7*J7,IF(F7="Manual Annual",SUM(K7:V7),0))) -> 0 | AA7: 0 | AB7: =IFERROR((Z7-AA7)/AA7,0) -> 0 | AC7: Medium | AD7: School Fees
A8: BL-003 | B8: INCOME | C8: Breakfast | F8: Monthly | G8: 0 | H8: Other | I8: 0 | J8: 1 | K8: 0 | L8: 0 | M8: 0 | N8: 0 | O8: 0 | P8: 0 | Q8: 0 | R8: 0 | S8: 0 | T8: 0 | U8: 0 | V8: 0 | W8: =SUM(K8:N8) -> 0 | X8: =SUM(O8:R8) -> 0 | Y8: =SUM(S8:V8) -> 0 | Z8: =IF(F8="Monthly",SUM(K8:V8),IF(F8="Unit-based",G8*I8*J8,IF(F8="Manual Annual",SUM(K8:V8),0))) -> 0 | AA8: 0 | AB8: =IFERROR((Z8-AA8)/AA8,0) -> 0 | AC8: Medium | AD8: School Fees
A9: BL-004 | B9: INCOME | C9: Transport | F9: Monthly | G9: 0 | H9: Other | I9: 0 | J9: 1 | K9: 0 | L9: 0 | M9: 0 | N9: 0 | O9: 0 | P9: 0 | Q9: 0 | R9: 0 | S9: 0 | T9: 0 | U9: 0 | V9: 0 | W9: =SUM(K9:N9) -> 0 | X9: =SUM(O9:R9) -> 0 | Y9: =SUM(S9:V9) -> 0 | Z9: =IF(F9="Monthly",SUM(K9:V9),IF(F9="Unit-based",G9*I9*J9,IF(F9="Manual Annual",SUM(K9:V9),0))) -> 0 | AA9: 0 | AB9: =IFERROR((Z9-AA9)/AA9,0) -> 0 | AC9: Medium | AD9: School Fees
A10: BL-005 | B10: INCOME | C10: Other Fees | F10: Monthly | G10: 0 | H10: Other | I10: 0 | J10: 1 | K10: 0 | L10: 0 | M10: 0 | N10: 0 | O10: 0 | P10: 0 | Q10: 0 | R10: 0 | S10: 0 | T10: 0 | U10: 0 | V10: 0 | W10: =SUM(K10:N10) -> 0 | X10: =SUM(O10:R10) -> 0 | Y10: =SUM(S10:V10) -> 0 | Z10: =IF(F10="Monthly",SUM(K10:V10),IF(F10="Unit-based",G10*I10*J10,IF(F10="Manual Annual",SUM(K10:V10),0))) -> 0 | AA10: 0 | AB10: =IFERROR((Z10-AA10)/AA10,0) -> 0 | AC10: Medium | AD10: School Fees
A11: BL-006 | B11: OPERATING EXPENSES | C11: School Materials | F11: Monthly | G11: 0 | H11: Other | I11: 0 | J11: 1 | K11: 0 | L11: 0 | M11: 0 | N11: 0 | O11: 0 | P11: 0 | Q11: 0 | R11: 0 | S11: 0 | T11: 0 | U11: 0 | V11: 0 | W11: =SUM(K11:N11) -> 0 | X11: =SUM(O11:R11) -> 0 | Y11: =SUM(S11:V11) -> 0 | Z11: =IF(F11="Monthly",SUM(K11:V11),IF(F11="Unit-based",G11*I11*J11,IF(F11="Manual Annual",SUM(K11:V11),0))) -> 0 | AA11: 0 | AB11: =IFERROR((Z11-AA11)/AA11,0) -> 0 | AC11: Medium | AD11: School Fees
A12: BL-007 | B12: OPERATING EXPENSES | C12: Food Expenses | F12: Monthly | G12: 0 | H12: Other | I12: 0 | J12: 1 | K12: 0 | L12: 0 | M12: 0 | N12: 0 | O12: 0 | P12: 0 | Q12: 0 | R12: 0 | S12: 0 | T12: 0 | U12: 0 | V12: 0 | W12: =SUM(K12:N12) -> 0 | X12: =SUM(O12:R12) -> 0 | Y12: =SUM(S12:V12) -> 0 | Z12: =IF(F12="Monthly",SUM(K12:V12),IF(F12="Unit-based",G12*I12*J12,IF(F12="Manual Annual",SUM(K12:V12),0))) -> 0 | AA12: 0 | AB12: =IFERROR((Z12-AA12)/AA12,0) -> 0 | AC12: Medium | AD12: School Fees
A13: BL-008 | B13: OPERATING EXPENSES | C13: Travel, Mission & Transport Expenses | F13: Monthly | G13: 0 | H13: Other | I13: 0 | J13: 1 | K13: 0 | L13: 0 | M13: 0 | N13: 0 | O13: 0 | P13: 0 | Q13: 0 | R13: 0 | S13: 0 | T13: 0 | U13: 0 | V13: 0 | W13: =SUM(K13:N13) -> 0 | X13: =SUM(O13:R13) -> 0 | Y13: =SUM(S13:V13) -> 0 | Z13: =IF(F13="Monthly",SUM(K13:V13),IF(F13="Unit-based",G13*I13*J13,IF(F13="Manual Annual",SUM(K13:V13),0))) -> 0 | AA13: 0 | AB13: =IFERROR((Z13-AA13)/AA13,0) -> 0 | AC13: Medium | AD13: School Fees
A14: BL-009 | B14: OPERATING EXPENSES | C14: Fuel | F14: Monthly | G14: 0 | H14: Other | I14: 0 | J14: 1 | K14: 0 | L14: 0 | M14: 0 | N14: 0 | O14: 0 | P14: 0 | Q14: 0 | R14: 0 | S14: 0 | T14: 0 | U14: 0 | V14: 0 | W14: =SUM(K14:N14) -> 0 | X14: =SUM(O14:R14) -> 0 | Y14: =SUM(S14:V14) -> 0 | Z14: =IF(F14="Monthly",SUM(K14:V14),IF(F14="Unit-based",G14*I14*J14,IF(F14="Manual Annual",SUM(K14:V14),0))) -> 0 | AA14: 0 | AB14: =IFERROR((Z14-AA14)/AA14,0) -> 0 | AC14: Medium | AD14: School Fees
A15: BL-010 | B15: OPERATING EXPENSES | C15: Vehicle Maintenance | F15: Monthly | G15: 0 | H15: Other | I15: 0 | J15: 1 | K15: 0 | L15: 0 | M15: 0 | N15: 0 | O15: 0 | P15: 0 | Q15: 0 | R15: 0 | S15: 0 | T15: 0 | U15: 0 | V15: 0 | W15: =SUM(K15:N15) -> 0 | X15: =SUM(O15:R15) -> 0 | Y15: =SUM(S15:V15) -> 0 | Z15: =IF(F15="Monthly",SUM(K15:V15),IF(F15="Unit-based",G15*I15*J15,IF(F15="Manual Annual",SUM(K15:V15),0))) -> 0 | AA15: 0 | AB15: =IFERROR((Z15-AA15)/AA15,0) -> 0 | AC15: Medium | AD15: School Fees
A16: BL-011 | B16: OPERATING EXPENSES | C16: Utilities (Water & Electricity) | F16: Monthly | G16: 0 | H16: Other | I16: 0 | J16: 1 | K16: 0 | L16: 0 | M16: 0 | N16: 0 | O16: 0 | P16: 0 | Q16: 0 | R16: 0 | S16: 0 | T16: 0 | U16: 0 | V16: 0 | W16: =SUM(K16:N16) -> 0 | X16: =SUM(O16:R16) -> 0 | Y16: =SUM(S16:V16) -> 0 | Z16: =IF(F16="Monthly",SUM(K16:V16),IF(F16="Unit-based",G16*I16*J16,IF(F16="Manual Annual",SUM(K16:V16),0))) -> 0 | AA16: 0 | AB16: =IFERROR((Z16-AA16)/AA16,0) -> 0 | AC16: Medium | AD16: School Fees
A17: BL-012 | B17: OPERATING EXPENSES | C17: Rental Expenses | F17: Monthly | G17: 0 | H17: Other | I17: 0 | J17: 1 | K17: 0 | L17: 0 | M17: 0 | N17: 0 | O17: 0 | P17: 0 | Q17: 0 | R17: 0 | S17: 0 | T17: 0 | U17: 0 | V17: 0 | W17: =SUM(K17:N17) -> 0 | X17: =SUM(O17:R17) -> 0 | Y17: =SUM(S17:V17) -> 0 | Z17: =IF(F17="Monthly",SUM(K17:V17),IF(F17="Unit-based",G17*I17*J17,IF(F17="Manual Annual",SUM(K17:V17),0))) -> 0 | AA17: 0 | AB17: =IFERROR((Z17-AA17)/AA17,0) -> 0 | AC17: Medium | AD17: School Fees
... A32: BL-027 | B32: FINANCE COSTS | C32: Bank Charges & Account Maintenance Fees | F32: Monthly | G32: 0 | H32: Other | I32: 0 | J32: 1 | K32: 0 | L32: 0 | M32: 0 | N32: 0 | O32: 0 | P32: 0 | Q32: 0 | R32: 0 | S32: 0 | T32: 0 | U32: 0 | V32: 0 | W32: =SUM(K32:N32) -> 0 | X32: =SUM(O32:R32) -> 0 | Y32: =SUM(S32:V32) -> 0 | Z32: =IF(F32="Monthly",SUM(K32:V32),IF(F32="Unit-based",G32*I32*J32,IF(F32="Manual Annual",SUM(K32:V32),0))) -> 0 | AA32: 0 | AB32: =IFERROR((Z32-AA32)/AA32,0) -> 0 | AC32: Medium | AD32: School Fees
A33: BL-028 | F33: Monthly | G33: 0 | H33: Other | I33: 0 | J33: 1 | K33: 0 | L33: 0 | M33: 0 | N33: 0 | O33: 0 | P33: 0 | Q33: 0 | R33: 0 | S33: 0 | T33: 0 | U33: 0 | V33: 0 | W33: =SUM(K33:N33) -> 0 | X33: =SUM(O33:R33) -> 0 | Y33: =SUM(S33:V33) -> 0 | Z33: =IF(F33="Monthly",SUM(K33:V33),IF(F33="Unit-based",G33*I33*J33,IF(F33="Manual Annual",SUM(K33:V33),0))) -> 0 | AA33: 0 | AB33: =IFERROR((Z33-AA33)/AA33,0) -> 0 | AC33: Medium | AD33: School Fees
A34: BL-029 | F34: Monthly | G34: 0 | H34: Other | I34: 0 | J34: 1 | K34: 0 | L34: 0 | M34: 0 | N34: 0 | O34: 0 | P34: 0 | Q34: 0 | R34: 0 | S34: 0 | T34: 0 | U34: 0 | V34: 0 | W34: =SUM(K34:N34) -> 0 | X34: =SUM(O34:R34) -> 0 | Y34: =SUM(S34:V34) -> 0 | Z34: =IF(F34="Monthly",SUM(K34:V34),IF(F34="Unit-based",G34*I34*J34,IF(F34="Manual Annual",SUM(K34:V34),0))) -> 0 | AA34: 0 | AB34: =IFERROR((Z34-AA34)/AA34,0) -> 0 | AC34: Medium | AD34: School Fees
A35: BL-030 | F35: Monthly | G35: 0 | H35: Other | I35: 0 | J35: 1 | K35: 0 | L35: 0 | M35: 0 | N35: 0 | O35: 0 | P35: 0 | Q35: 0 | R35: 0 | S35: 0 | T35: 0 | U35: 0 | V35: 0 | W35: =SUM(K35:N35) -> 0 | X35: =SUM(O35:R35) -> 0 | Y35: =SUM(S35:V35) -> 0 | Z35: =IF(F35="Monthly",SUM(K35:V35),IF(F35="Unit-based",G35*I35*J35,IF(F35="Manual Annual",SUM(K35:V35),0))) -> 0 | AA35: 0 | AB35: =IFERROR((Z35-AA35)/AA35,0) -> 0 | AC35: Medium | AD35: School Fees
A36: BL-031 | F36: Monthly | G36: 0 | H36: Other | I36: 0 | J36: 1 | K36: 0 | L36: 0 | M36: 0 | N36: 0 | O36: 0 | P36: 0 | Q36: 0 | R36: 0 | S36: 0 | T36: 0 | U36: 0 | V36: 0 | W36: =SUM(K36:N36) -> 0 | X36: =SUM(O36:R36) -> 0 | Y36: =SUM(S36:V36) -> 0 | Z36: =IF(F36="Monthly",SUM(K36:V36),IF(F36="Unit-based",G36*I36*J36,IF(F36="Manual Annual",SUM(K36:V36),0))) -> 0 | AA36: 0 | AB36: =IFERROR((Z36-AA36)/AA36,0) -> 0 | AC36: Medium | AD36: School Fees
A37: BL-032 | F37: Monthly | G37: 0 | H37: Other | I37: 0 | J37: 1 | K37: 0 | L37: 0 | M37: 0 | N37: 0 | O37: 0 | P37: 0 | Q37: 0 | R37: 0 | S37: 0 | T37: 0 | U37: 0 | V37: 0 | W37: =SUM(K37:N37) -> 0 | X37: =SUM(O37:R37) -> 0 | Y37: =SUM(S37:V37) -> 0 | Z37: =IF(F37="Monthly",SUM(K37:V37),IF(F37="Unit-based",G37*I37*J37,IF(F37="Manual Annual",SUM(K37:V37),0))) -> 0 | AA37: 0 | AB37: =IFERROR((Z37-AA37)/AA37,0) -> 0 | AC37: Medium | AD37: School Fees
A38: BL-033 | F38: Monthly | G38: 0 | H38: Other | I38: 0 | J38: 1 | K38: 0 | L38: 0 | M38: 0 | N38: 0 | O38: 0 | P38: 0 | Q38: 0 | R38: 0 | S38: 0 | T38: 0 | U38: 0 | V38: 0 | W38: =SUM(K38:N38) -> 0 | X38: =SUM(O38:R38) -> 0 | Y38: =SUM(S38:V38) -> 0 | Z38: =IF(F38="Monthly",SUM(K38:V38),IF(F38="Unit-based",G38*I38*J38,IF(F38="Manual Annual",SUM(K38:V38),0))) -> 0 | AA38: 0 | AB38: =IFERROR((Z38-AA38)/AA38,0) -> 0 | AC38: Medium | AD38: School Fees
A39: BL-034 | F39: Monthly | G39: 0 | H39: Other | I39: 0 | J39: 1 | K39: 0 | L39: 0 | M39: 0 | N39: 0 | O39: 0 | P39: 0 | Q39: 0 | R39: 0 | S39: 0 | T39: 0 | U39: 0 | V39: 0 | W39: =SUM(K39:N39) -> 0 | X39: =SUM(O39:R39) -> 0 | Y39: =SUM(S39:V39) -> 0 | Z39: =IF(F39="Monthly",SUM(K39:V39),IF(F39="Unit-based",G39*I39*J39,IF(F39="Manual Annual",SUM(K39:V39),0))) -> 0 | AA39: 0 | AB39: =IFERROR((Z39-AA39)/AA39,0) -> 0 | AC39: Medium | AD39: School Fees
A40: BL-035 | F40: Monthly | G40: 0 | H40: Other | I40: 0 | J40: 1 | K40: 0 | L40: 0 | M40: 0 | N40: 0 | O40: 0 | P40: 0 | Q40: 0 | R40: 0 | S40: 0 | T40: 0 | U40: 0 | V40: 0 | W40: =SUM(K40:N40) -> 0 | X40: =SUM(O40:R40) -> 0 | Y40: =SUM(S40:V40) -> 0 | Z40: =IF(F40="Monthly",SUM(K40:V40),IF(F40="Unit-based",G40*I40*J40,IF(F40="Manual Annual",SUM(K40:V40),0))) -> 0 | AA40: 0 | AB40: =IFERROR((Z40-AA40)/AA40,0) -> 0 | AC40: Medium | AD40: School Fees
T42: TOTAL INCOME | Z42: =SUMIF($B$6:$B$40,"INCOME",$Z$6:$Z$40) -> 0
T43: TOTAL OPERATING EXPENSES | Z43: =SUMIF($B$6:$B$40,"OPERATING EXPENSES",$Z$6:$Z$40) -> 0
T44: TOTAL ADMINISTRATIVE COSTS | Z44: =SUMIF($B$6:$B$40,"ADMINISTRATIVE COSTS",$Z$6:$Z$40) -> 0
T45: TOTAL FINANCE COSTS | Z45: =SUMIF($B$6:$B$40,"FINANCE COSTS",$Z$6:$Z$40) -> 0
T46: TOTAL EXPENSES | Z46: =SUM(Z43:Z45) -> 0
T47: BUDGET SURPLUS / (DEFICIT) | Z47: =Z42-Z46 -> 0

Sheet CASH_FLOW
A1: MONTHLY CASH FLOW FORECAST
A3: Branch | B3: =SETUP!B6 -> Musanze | E3: Budget Year | F3: =SETUP!B8 -> 2027 | I3: Currency | J3: =SETUP!B12 -> RWF
A5: Cash Flow Item | B5: Jan | C5: Feb | D5: Mar | E5: Apr | F5: May | G5: Jun | H5: Jul | I5: Aug | J5: Sep | K5: Oct | L5: Nov | M5: Dec | N5: Annual Total | O5: % of Total
A6: Cash Inflows
A7: School Fees | B7: =SUMIFS(BUDGET_PLAN!$K$6:$K$40,BUDGET_PLAN!$C$6:$C$40,$A7) -> 0 | C7: =SUMIFS(BUDGET_PLAN!$L$6:$L$40,BUDGET_PLAN!$C$6:$C$40,$A7) -> 0 | D7: =SUMIFS(BUDGET_PLAN!$M$6:$M$40,BUDGET_PLAN!$C$6:$C$40,$A7) -> 0 | E7: =SUMIFS(BUDGET_PLAN!$N$6:$N$40,BUDGET_PLAN!$C$6:$C$40,$A7) -> 0 | F7: =SUMIFS(BUDGET_PLAN!$O$6:$O$40,BUDGET_PLAN!$C$6:$C$40,$A7) -> 0 | G7: =SUMIFS(BUDGET_PLAN!$P$6:$P$40,BUDGET_PLAN!$C$6:$C$40,$A7) -> 0 | H7: =SUMIFS(BUDGET_PLAN!$Q$6:$Q$40,BUDGET_PLAN!$C$6:$C$40,$A7) -> 0 | I7: =SUMIFS(BUDGET_PLAN!$R$6:$R$40,BUDGET_PLAN!$C$6:$C$40,$A7) -> 0 | J7: =SUMIFS(BUDGET_PLAN!$S$6:$S$40,BUDGET_PLAN!$C$6:$C$40,$A7) -> 0 | K7: =SUMIFS(BUDGET_PLAN!$T$6:$T$40,BUDGET_PLAN!$C$6:$C$40,$A7) -> 0 | L7: =SUMIFS(BUDGET_PLAN!$U$6:$U$40,BUDGET_PLAN!$C$6:$C$40,$A7) -> 0 | M7: =SUMIFS(BUDGET_PLAN!$V$6:$V$40,BUDGET_PLAN!$C$6:$C$40,$A7) -> 0 | N7: =SUM(B7:M7) -> 0 | O7: =IFERROR(N7/$N$12,0) -> 0
A8: Lunch | B8: =SUMIFS(BUDGET_PLAN!$K$6:$K$40,BUDGET_PLAN!$C$6:$C$40,$A8) -> 0 | C8: =SUMIFS(BUDGET_PLAN!$L$6:$L$40,BUDGET_PLAN!$C$6:$C$40,$A8) -> 0 | D8: =SUMIFS(BUDGET_PLAN!$M$6:$M$40,BUDGET_PLAN!$C$6:$C$40,$A8) -> 0 | E8: =SUMIFS(BUDGET_PLAN!$N$6:$N$40,BUDGET_PLAN!$C$6:$C$40,$A8) -> 0 | F8: =SUMIFS(BUDGET_PLAN!$O$6:$O$40,BUDGET_PLAN!$C$6:$C$40,$A8) -> 0 | G8: =SUMIFS(BUDGET_PLAN!$P$6:$P$40,BUDGET_PLAN!$C$6:$C$40,$A8) -> 0 | H8: =SUMIFS(BUDGET_PLAN!$Q$6:$Q$40,BUDGET_PLAN!$C$6:$C$40,$A8) -> 0 | I8: =SUMIFS(BUDGET_PLAN!$R$6:$R$40,BUDGET_PLAN!$C$6:$C$40,$A8) -> 0 | J8: =SUMIFS(BUDGET_PLAN!$S$6:$S$40,BUDGET_PLAN!$C$6:$C$40,$A8) -> 0 | K8: =SUMIFS(BUDGET_PLAN!$T$6:$T$40,BUDGET_PLAN!$C$6:$C$40,$A8) -> 0 | L8: =SUMIFS(BUDGET_PLAN!$U$6:$U$40,BUDGET_PLAN!$C$6:$C$40,$A8) -> 0 | M8: =SUMIFS(BUDGET_PLAN!$V$6:$V$40,BUDGET_PLAN!$C$6:$C$40,$A8) -> 0 | N8: =SUM(B8:M8) -> 0 | O8: =IFERROR(N8/$N$12,0) -> 0
A9: Breakfast | B9: =SUMIFS(BUDGET_PLAN!$K$6:$K$40,BUDGET_PLAN!$C$6:$C$40,$A9) -> 0 | C9: =SUMIFS(BUDGET_PLAN!$L$6:$L$40,BUDGET_PLAN!$C$6:$C$40,$A9) -> 0 | D9: =SUMIFS(BUDGET_PLAN!$M$6:$M$40,BUDGET_PLAN!$C$6:$C$40,$A9) -> 0 | E9: =SUMIFS(BUDGET_PLAN!$N$6:$N$40,BUDGET_PLAN!$C$6:$C$40,$A9) -> 0 | F9: =SUMIFS(BUDGET_PLAN!$O$6:$O$40,BUDGET_PLAN!$C$6:$C$40,$A9) -> 0 | G9: =SUMIFS(BUDGET_PLAN!$P$6:$P$40,BUDGET_PLAN!$C$6:$C$40,$A9) -> 0 | H9: =SUMIFS(BUDGET_PLAN!$Q$6:$Q$40,BUDGET_PLAN!$C$6:$C$40,$A9) -> 0 | I9: =SUMIFS(BUDGET_PLAN!$R$6:$R$40,BUDGET_PLAN!$C$6:$C$40,$A9) -> 0 | J9: =SUMIFS(BUDGET_PLAN!$S$6:$S$40,BUDGET_PLAN!$C$6:$C$40,$A9) -> 0 | K9: =SUMIFS(BUDGET_PLAN!$T$6:$T$40,BUDGET_PLAN!$C$6:$C$40,$A9) -> 0 | L9: =SUMIFS(BUDGET_PLAN!$U$6:$U$40,BUDGET_PLAN!$C$6:$C$40,$A9) -> 0 | M9: =SUMIFS(BUDGET_PLAN!$V$6:$V$40,BUDGET_PLAN!$C$6:$C$40,$A9) -> 0 | N9: =SUM(B9:M9) -> 0 | O9: =IFERROR(N9/$N$12,0) -> 0
A10: Transport | B10: =SUMIFS(BUDGET_PLAN!$K$6:$K$40,BUDGET_PLAN!$C$6:$C$40,$A10) -> 0 | C10: =SUMIFS(BUDGET_PLAN!$L$6:$L$40,BUDGET_PLAN!$C$6:$C$40,$A10) -> 0 | D10: =SUMIFS(BUDGET_PLAN!$M$6:$M$40,BUDGET_PLAN!$C$6:$C$40,$A10) -> 0 | E10: =SUMIFS(BUDGET_PLAN!$N$6:$N$40,BUDGET_PLAN!$C$6:$C$40,$A10) -> 0 | F10: =SUMIFS(BUDGET_PLAN!$O$6:$O$40,BUDGET_PLAN!$C$6:$C$40,$A10) -> 0 | G10: =SUMIFS(BUDGET_PLAN!$P$6:$P$40,BUDGET_PLAN!$C$6:$C$40,$A10) -> 0 | H10: =SUMIFS(BUDGET_PLAN!$Q$6:$Q$40,BUDGET_PLAN!$C$6:$C$40,$A10) -> 0 | I10: =SUMIFS(BUDGET_PLAN!$R$6:$R$40,BUDGET_PLAN!$C$6:$C$40,$A10) -> 0 | J10: =SUMIFS(BUDGET_PLAN!$S$6:$S$40,BUDGET_PLAN!$C$6:$C$40,$A10) -> 0 | K10: =SUMIFS(BUDGET_PLAN!$T$6:$T$40,BUDGET_PLAN!$C$6:$C$40,$A10) -> 0 | L10: =SUMIFS(BUDGET_PLAN!$U$6:$U$40,BUDGET_PLAN!$C$6:$C$40,$A10) -> 0 | M10: =SUMIFS(BUDGET_PLAN!$V$6:$V$40,BUDGET_PLAN!$C$6:$C$40,$A10) -> 0 | N10: =SUM(B10:M10) -> 0 | O10: =IFERROR(N10/$N$12,0) -> 0
A11: Other Fees | B11: =SUMIFS(BUDGET_PLAN!$K$6:$K$40,BUDGET_PLAN!$C$6:$C$40,$A11) -> 0 | C11: =SUMIFS(BUDGET_PLAN!$L$6:$L$40,BUDGET_PLAN!$C$6:$C$40,$A11) -> 0 | D11: =SUMIFS(BUDGET_PLAN!$M$6:$M$40,BUDGET_PLAN!$C$6:$C$40,$A11) -> 0 | E11: =SUMIFS(BUDGET_PLAN!$N$6:$N$40,BUDGET_PLAN!$C$6:$C$40,$A11) -> 0 | F11: =SUMIFS(BUDGET_PLAN!$O$6:$O$40,BUDGET_PLAN!$C$6:$C$40,$A11) -> 0 | G11: =SUMIFS(BUDGET_PLAN!$P$6:$P$40,BUDGET_PLAN!$C$6:$C$40,$A11) -> 0 | H11: =SUMIFS(BUDGET_PLAN!$Q$6:$Q$40,BUDGET_PLAN!$C$6:$C$40,$A11) -> 0 | I11: =SUMIFS(BUDGET_PLAN!$R$6:$R$40,BUDGET_PLAN!$C$6:$C$40,$A11) -> 0 | J11: =SUMIFS(BUDGET_PLAN!$S$6:$S$40,BUDGET_PLAN!$C$6:$C$40,$A11) -> 0 | K11: =SUMIFS(BUDGET_PLAN!$T$6:$T$40,BUDGET_PLAN!$C$6:$C$40,$A11) -> 0 | L11: =SUMIFS(BUDGET_PLAN!$U$6:$U$40,BUDGET_PLAN!$C$6:$C$40,$A11) -> 0 | M11: =SUMIFS(BUDGET_PLAN!$V$6:$V$40,BUDGET_PLAN!$C$6:$C$40,$A11) -> 0 | N11: =SUM(B11:M11) -> 0 | O11: =IFERROR(N11/$N$12,0) -> 0
A12: TOTAL CASH INFLOWS | B12: =SUM(B7:B11) -> 0 | C12: =SUM(C7:C11) -> 0 | D12: =SUM(D7:D11) -> 0 | E12: =SUM(E7:E11) -> 0 | F12: =SUM(F7:F11) -> 0 | G12: =SUM(G7:G11) -> 0 | H12: =SUM(H7:H11) -> 0 | I12: =SUM(I7:I11) -> 0 | ... M12: =SUM(M7:M11) -> 0 | N12: =SUM(B12:M12) -> 0 | O12: =IFERROR(N12/$N$12,0) -> 0
A14: Cash Outflows
A15: Operating Expenses | B15: =SUMIFS(BUDGET_PLAN!$K$6:$K$40,BUDGET_PLAN!$B$6:$B$40,"OPERATING EXPENSES") -> 0 | C15: =SUMIFS(BUDGET_PLAN!$L$6:$L$40,BUDGET_PLAN!$B$6:$B$40,"OPERATING EXPENSES") -> 0 | D15: =SUMIFS(BUDGET_PLAN!$M$6:$M$40,BUDGET_PLAN!$B$6:$B$40,"OPERATING EXPENSES") -> 0 | E15: =SUMIFS(BUDGET_PLAN!$N$6:$N$40,BUDGET_PLAN!$B$6:$B$40,"OPERATING EXPENSES") -> 0 | F15: =SUMIFS(BUDGET_PLAN!$O$6:$O$40,BUDGET_PLAN!$B$6:$B$40,"OPERATING EXPENSES") -> 0 | G15: =SUMIFS(BUDGET_PLAN!$P$6:$P$40,BUDGET_PLAN!$B$6:$B$40,"OPERATING EXPENSES") -> 0 | H15: =SUMIFS(BUDGET_PLAN!$Q$6:$Q$40,BUDGET_PLAN!$B$6:$B$40,"OPERATING EXPENSES") -> 0 | I15: =SUMIFS(BUDGET_PLAN!$R$6:$R$40,BUDGET_PLAN!$B$6:$B$40,"OPERATING EXPENSES") -> 0 | J15: =SUMIFS(BUDGET_PLAN!$S$6:$S$40,BUDGET_PLAN!$B$6:$B$40,"OPERATING EXPENSES") -> 0 | K15: =SUMIFS(BUDGET_PLAN!$T$6:$T$40,BUDGET_PLAN!$B$6:$B$40,"OPERATING EXPENSES") -> 0 | L15: =SUMIFS(BUDGET_PLAN!$U$6:$U$40,BUDGET_PLAN!$B$6:$B$40,"OPERATING EXPENSES") -> 0 | M15: =SUMIFS(BUDGET_PLAN!$V$6:$V$40,BUDGET_PLAN!$B$6:$B$40,"OPERATING EXPENSES") -> 0 | N15: =SUM(B15:M15) -> 0 | O15: =IFERROR(N15/$N$18,0) -> 0
A16: Administrative Costs | B16: =SUMIFS(BUDGET_PLAN!$K$6:$K$40,BUDGET_PLAN!$B$6:$B$40,"ADMINISTRATIVE COSTS") -> 0 | C16: =SUMIFS(BUDGET_PLAN!$L$6:$L$40,BUDGET_PLAN!$B$6:$B$40,"ADMINISTRATIVE COSTS") -> 0 | D16: =SUMIFS(BUDGET_PLAN!$M$6:$M$40,BUDGET_PLAN!$B$6:$B$40,"ADMINISTRATIVE COSTS") -> 0 | E16: =SUMIFS(BUDGET_PLAN!$N$6:$N$40,BUDGET_PLAN!$B$6:$B$40,"ADMINISTRATIVE COSTS") -> 0 | F16: =SUMIFS(BUDGET_PLAN!$O$6:$O$40,BUDGET_PLAN!$B$6:$B$40,"ADMINISTRATIVE COSTS") -> 0 | G16: =SUMIFS(BUDGET_PLAN!$P$6:$P$40,BUDGET_PLAN!$B$6:$B$40,"ADMINISTRATIVE COSTS") -> 0 | H16: =SUMIFS(BUDGET_PLAN!$Q$6:$Q$40,BUDGET_PLAN!$B$6:$B$40,"ADMINISTRATIVE COSTS") -> 0 | I16: =SUMIFS(BUDGET_PLAN!$R$6:$R$40,BUDGET_PLAN!$B$6:$B$40,"ADMINISTRATIVE COSTS") -> 0 | J16: =SUMIFS(BUDGET_PLAN!$S$6:$S$40,BUDGET_PLAN!$B$6:$B$40,"ADMINISTRATIVE COSTS") -> 0 | K16: =SUMIFS(BUDGET_PLAN!$T$6:$T$40,BUDGET_PLAN!$B$6:$B$40,"ADMINISTRATIVE COSTS") -> 0 | L16: =SUMIFS(BUDGET_PLAN!$U$6:$U$40,BUDGET_PLAN!$B$6:$B$40,"ADMINISTRATIVE COSTS") -> 0 | M16: =SUMIFS(BUDGET_PLAN!$V$6:$V$40,BUDGET_PLAN!$B$6:$B$40,"ADMINISTRATIVE COSTS") -> 0 | N16: =SUM(B16:M16) -> 0 | O16: =IFERROR(N16/$N$18,0) -> 0
A17: Finance Costs | B17: =SUMIFS(BUDGET_PLAN!$K$6:$K$40,BUDGET_PLAN!$B$6:$B$40,"FINANCE COSTS") -> 0 | C17: =SUMIFS(BUDGET_PLAN!$L$6:$L$40,BUDGET_PLAN!$B$6:$B$40,"FINANCE COSTS") -> 0 | D17: =SUMIFS(BUDGET_PLAN!$M$6:$M$40,BUDGET_PLAN!$B$6:$B$40,"FINANCE COSTS") -> 0 | E17: =SUMIFS(BUDGET_PLAN!$N$6:$N$40,BUDGET_PLAN!$B$6:$B$40,"FINANCE COSTS") -> 0 | F17: =SUMIFS(BUDGET_PLAN!$O$6:$O$40,BUDGET_PLAN!$B$6:$B$40,"FINANCE COSTS") -> 0 | G17: =SUMIFS(BUDGET_PLAN!$P$6:$P$40,BUDGET_PLAN!$B$6:$B$40,"FINANCE COSTS") -> 0 | H17: =SUMIFS(BUDGET_PLAN!$Q$6:$Q$40,BUDGET_PLAN!$B$6:$B$40,"FINANCE COSTS") -> 0 | I17: =SUMIFS(BUDGET_PLAN!$R$6:$R$40,BUDGET_PLAN!$B$6:$B$40,"FINANCE COSTS") -> 0 | J17: =SUMIFS(BUDGET_PLAN!$S$6:$S$40,BUDGET_PLAN!$B$6:$B$40,"FINANCE COSTS") -> 0 | K17: =SUMIFS(BUDGET_PLAN!$T$6:$T$40,BUDGET_PLAN!$B$6:$B$40,"FINANCE COSTS") -> 0 | L17: =SUMIFS(BUDGET_PLAN!$U$6:$U$40,BUDGET_PLAN!$B$6:$B$40,"FINANCE COSTS") -> 0 | M17: =SUMIFS(BUDGET_PLAN!$V$6:$V$40,BUDGET_PLAN!$B$6:$B$40,"FINANCE COSTS") -> 0 | N17: =SUM(B17:M17) -> 0 | O17: =IFERROR(N17/$N$18,0) -> 0
A18: TOTAL CASH OUTFLOWS | B18: =SUM(B15:B17) -> 0 | C18: =SUM(C15:C17) -> 0 | D18: =SUM(D15:D17) -> 0 | E18: =SUM(E15:E17) -> 0 | F18: =SUM(F15:F17) -> 0 | G18: =SUM(G15:G17) -> 0 | H18: =SUM(H15:H17) -> 0 | I18: =SUM(I15:I17) -> 0 | ... M18: =SUM(M15:M17) -> 0 | N18: =SUM(B18:M18) -> 0 | O18: =IFERROR(N18/$N$18,0) -> 0
A19: NET CASH FLOW | B19: =B12-B18 -> 0 | C19: =C12-C18 -> 0 | D19: =D12-D18 -> 0 | E19: =E12-E18 -> 0 | F19: =F12-F18 -> 0 | G19: =G12-G18 -> 0 | H19: =H12-H18 -> 0 | I19: =I12-I18 -> 0 | ... M19: =M12-M18 -> 0 | N19: =SUM(B19:M19) -> 0 | O19: =IFERROR(N19/$N$18,0) -> 0
A20: Opening Cash Balance | B20: 0 | C20: =B21 -> 0 | D20: =C21 -> 0 | E20: =D21 -> 0 | F20: =E21 -> 0 | G20: =F21 -> 0 | H20: =G21 -> 0 | I20: =H21 -> 0 | J20: =I21 -> 0 | ... M20: =L21 -> 0 | N20: =SUM(B20:M20) -> 0 | O20: =IFERROR(N20/$N$18,0) -> 0
A21: Closing Cash Balance | B21: =B20+B19 -> 0 | C21: =C20+C19 -> 0 | D21: =D20+D19 -> 0 | E21: =E20+E19 -> 0 | F21: =F20+F19 -> 0 | G21: =G20+G19 -> 0 | H21: =H20+H19 -> 0 | I21: =I20+I19 -> 0 | ... M21: =M20+M19 -> 0 | N21: =SUM(B21:M21) -> 0 | O21: =IFERROR(N21/$N$18,0) -> 0
A22: Minimum Cash Buffer | B22: =SETUP!B30 -> 0 | C22: =SETUP!B30 -> 0 | D22: =SETUP!B30 -> 0 | E22: =SETUP!B30 -> 0 | F22: =SETUP!B30 -> 0 | G22: =SETUP!B30 -> 0 | H22: =SETUP!B30 -> 0 | I22: =SETUP!B30 -> 0 | J22: =SETUP!B30 -> 0 | K22: =SETUP!B30 -> 0 | L22: =SETUP!B30 -> 0 | M22: =SETUP!B30 -> 0 | N22: =SUM(B22:M22) -> 0 | O22: =IFERROR(N22/$N$18,0) -> 0
A23: SURPLUS / (SHORTFALL) VS BUFFER | B23: =B21-B22 -> 0 | C23: =C21-C22 -> 0 | D23: =D21-D22 -> 0 | E23: =E21-E22 -> 0 | F23: =F21-F22 -> 0 | G23: =G21-G22 -> 0 | H23: =H21-H22 -> 0 | I23: =I21-I22 -> 0 | ... M23: =M21-M22 -> 0 | N23: =SUM(B23:M23) -> 0 | O23: =IFERROR(N23/$N$18,0) -> 0

Sheet BUDGET_SUMMARY
A1: MANAGEMENT BUDGET DASHBOARD
A3: Total Income | D3: Total Expenses | G3: Surplus / (Deficit) | J3: Expense Coverage
A4: =BUDGET_PLAN!Z42 -> 0 | D4: =BUDGET_PLAN!Z46 -> 0 | G4: =BUDGET_PLAN!Z47 -> 0 | J4: =IFERROR(BUDGET_PLAN!Z42/BUDGET_PLAN!Z46,0) -> 0
A8: BUDGET BY SECTION
A9: Section | B9: Annual Budget | C9: % of Total | D9: Previous Budget | E9: Variance | F9: Status
A10: INCOME | B10: =SUMIF(BUDGET_PLAN!$B$6:$B$40,A10,BUDGET_PLAN!$Z$6:$Z$40) -> 0 | C10: =IFERROR(B10/SUM($B$10:$B$13),0) -> 0 | D10: =SUMIF(BUDGET_PLAN!$B$6:$B$40,A10,BUDGET_PLAN!$AA$6:$AA$40) -> 0 | E10: =B10-D10 -> 0 | F10: =IF(E10>0,"Increase",IF(E10<0,"Decrease","No change")) -> No change
A11: OPERATING EXPENSES | B11: =SUMIF(BUDGET_PLAN!$B$6:$B$40,A11,BUDGET_PLAN!$Z$6:$Z$40) -> 0 | C11: =IFERROR(B11/SUM($B$10:$B$13),0) -> 0 | D11: =SUMIF(BUDGET_PLAN!$B$6:$B$40,A11,BUDGET_PLAN!$AA$6:$AA$40) -> 0 | E11: =B11-D11 -> 0 | F11: =IF(E11>0,"Increase",IF(E11<0,"Decrease","No change")) -> No change
A12: ADMINISTRATIVE COSTS | B12: =SUMIF(BUDGET_PLAN!$B$6:$B$40,A12,BUDGET_PLAN!$Z$6:$Z$40) -> 0 | C12: =IFERROR(B12/SUM($B$10:$B$13),0) -> 0 | D12: =SUMIF(BUDGET_PLAN!$B$6:$B$40,A12,BUDGET_PLAN!$AA$6:$AA$40) -> 0 | E12: =B12-D12 -> 0 | F12: =IF(E12>0,"Increase",IF(E12<0,"Decrease","No change")) -> No change
A13: FINANCE COSTS | B13: =SUMIF(BUDGET_PLAN!$B$6:$B$40,A13,BUDGET_PLAN!$Z$6:$Z$40) -> 0 | C13: =IFERROR(B13/SUM($B$10:$B$13),0) -> 0 | D13: =SUMIF(BUDGET_PLAN!$B$6:$B$40,A13,BUDGET_PLAN!$AA$6:$AA$40) -> 0 | E13: =B13-D13 -> 0 | F13: =IF(E13>0,"Increase",IF(E13<0,"Decrease","No change")) -> No change
A16: MONTHLY NET CASH FLOW
B17: Jan | C17: Feb | D17: Mar | E17: Apr | F17: May | G17: Jun | H17: Jul | I17: Aug | J17: Sep | K17: Oct | L17: Nov | M17: Dec
A18: Net Cash Flow | B18: =CASH_FLOW!B19 -> 0 | C18: =CASH_FLOW!C19 -> 0 | D18: =CASH_FLOW!D19 -> 0 | E18: =CASH_FLOW!E19 -> 0 | F18: =CASH_FLOW!F19 -> 0 | G18: =CASH_FLOW!G19 -> 0 | H18: =CASH_FLOW!H19 -> 0 | I18: =CASH_FLOW!I19 -> 0 | ... M18: =CASH_FLOW!M19 -> 0
A36: MANAGEMENT REVIEW CHECKLIST
A37: ☐ | B37: Budget balances or explains deficit | J37: Owner | K37: Due Date | L37: Status
A38: ☐ | B38: High-priority items are funded | J38: Owner | K38: Due Date | L38: Status
A39: ☐ | B39: Monthly cash shortfalls have mitigation plans | J39: Owner | K39: Due Date | L39: Status
A40: ☐ | B40: All material variances are explained | J40: Owner | K40: Due Date | L40: Status
A41: ☐ | B41: Procurement-sensitive items include assumptions | J41: Owner | K41: Due Date | L41: Status
A42: ☐ | B42: Budget Manager reviewed availability rules | J42: Owner | K42: Due Date | L42: Status
A43: ☐ | B43: Deputy Director approval is documented | J43: Owner | K43: Due Date | L43: Status

Sheet IMPORT_TEMPLATE
A1: SYSTEM IMPORT TEMPLATE – BUDGET MASTER DATA
A3: Use this clean table for uploading into School Settings. Do not modify header names after integration mapping is completed.
A5: template_version | B5: branch | C5: budget_year | D5: period | E5: line_id | F5: section | G5: category | H5: subcategory | I5: account_code | J5: calculation_mode | K5: quantity | L5: unit | M5: unit_cost | N5: frequency | O5: annual_amount | P5: priority | Q5: funding_source | R5: notes
A6: =SETUP!B17 -> 1.0 | B6: =SETUP!B6 -> Musanze | C6: =SETUP!B8 -> 2027 | D6: =SETUP!B9 -> Annual | E6: =BUDGET_PLAN!A6 -> BL-001 | F6: =BUDGET_PLAN!B6 -> INCOME | G6: =BUDGET_PLAN!C6 -> School Fees | H6: =BUDGET_PLAN!D6 -> 0 | I6: =BUDGET_PLAN!E6 -> 0 | J6: =BUDGET_PLAN!F6 -> Monthly | K6: =BUDGET_PLAN!G6 -> 0 | L6: =BUDGET_PLAN!H6 -> Other | ... N6: =BUDGET_PLAN!J6 -> 1 | O6: =BUDGET_PLAN!Z6 -> 0 | P6: =BUDGET_PLAN!AC6 -> Medium | Q6: =BUDGET_PLAN!AD6 -> School Fees | R6: =BUDGET_PLAN!AE6 -> 0
A7: =SETUP!B17 -> 1.0 | B7: =SETUP!B6 -> Musanze | C7: =SETUP!B8 -> 2027 | D7: =SETUP!B9 -> Annual | E7: =BUDGET_PLAN!A7 -> BL-002 | F7: =BUDGET_PLAN!B7 -> INCOME | G7: =BUDGET_PLAN!C7 -> Lunch | H7: =BUDGET_PLAN!D7 -> 0 | I7: =BUDGET_PLAN!E7 -> 0 | J7: =BUDGET_PLAN!F7 -> Monthly | K7: =BUDGET_PLAN!G7 -> 0 | L7: =BUDGET_PLAN!H7 -> Other | ... N7: =BUDGET_PLAN!J7 -> 1 | O7: =BUDGET_PLAN!Z7 -> 0 | P7: =BUDGET_PLAN!AC7 -> Medium | Q7: =BUDGET_PLAN!AD7 -> School Fees | R7: =BUDGET_PLAN!AE7 -> 0
A8: =SETUP!B17 -> 1.0 | B8: =SETUP!B6 -> Musanze | C8: =SETUP!B8 -> 2027 | D8: =SETUP!B9 -> Annual | E8: =BUDGET_PLAN!A8 -> BL-003 | F8: =BUDGET_PLAN!B8 -> INCOME | G8: =BUDGET_PLAN!C8 -> Breakfast | H8: =BUDGET_PLAN!D8 -> 0 | I8: =BUDGET_PLAN!E8 -> 0 | J8: =BUDGET_PLAN!F8 -> Monthly | K8: =BUDGET_PLAN!G8 -> 0 | L8: =BUDGET_PLAN!H8 -> Other | ... N8: =BUDGET_PLAN!J8 -> 1 | O8: =BUDGET_PLAN!Z8 -> 0 | P8: =BUDGET_PLAN!AC8 -> Medium | Q8: =BUDGET_PLAN!AD8 -> School Fees | R8: =BUDGET_PLAN!AE8 -> 0
A9: =SETUP!B17 -> 1.0 | B9: =SETUP!B6 -> Musanze | C9: =SETUP!B8 -> 2027 | D9: =SETUP!B9 -> Annual | E9: =BUDGET_PLAN!A9 -> BL-004 | F9: =BUDGET_PLAN!B9 -> INCOME | G9: =BUDGET_PLAN!C9 -> Transport | H9: =BUDGET_PLAN!D9 -> 0 | I9: =BUDGET_PLAN!E9 -> 0 | J9: =BUDGET_PLAN!F9 -> Monthly | K9: =BUDGET_PLAN!G9 -> 0 | L9: =BUDGET_PLAN!H9 -> Other | ... N9: =BUDGET_PLAN!J9 -> 1 | O9: =BUDGET_PLAN!Z9 -> 0 | P9: =BUDGET_PLAN!AC9 -> Medium | Q9: =BUDGET_PLAN!AD9 -> School Fees | R9: =BUDGET_PLAN!AE9 -> 0
A10: =SETUP!B17 -> 1.0 | B10: =SETUP!B6 -> Musanze | C10: =SETUP!B8 -> 2027 | D10: =SETUP!B9 -> Annual | E10: =BUDGET_PLAN!A10 -> BL-005 | F10: =BUDGET_PLAN!B10 -> INCOME | G10: =BUDGET_PLAN!C10 -> Other Fees | H10: =BUDGET_PLAN!D10 -> 0 | I10: =BUDGET_PLAN!E10 -> 0 | J10: =BUDGET_PLAN!F10 -> Monthly | K10: =BUDGET_PLAN!G10 -> 0 | L10: =BUDGET_PLAN!H10 -> Other | ... N10: =BUDGET_PLAN!J10 -> 1 | O10: =BUDGET_PLAN!Z10 -> 0 | P10: =BUDGET_PLAN!AC10 -> Medium | Q10: =BUDGET_PLAN!AD10 -> School Fees | R10: =BUDGET_PLAN!AE10 -> 0
A11: =SETUP!B17 -> 1.0 | B11: =SETUP!B6 -> Musanze | C11: =SETUP!B8 -> 2027 | D11: =SETUP!B9 -> Annual | E11: =BUDGET_PLAN!A11 -> BL-006 | F11: =BUDGET_PLAN!B11 -> OPERATING EXPENSES | G11: =BUDGET_PLAN!C11 -> School Materials | H11: =BUDGET_PLAN!D11 -> 0 | I11: =BUDGET_PLAN!E11 -> 0 | J11: =BUDGET_PLAN!F11 -> Monthly | K11: =BUDGET_PLAN!G11 -> 0 | L11: =BUDGET_PLAN!H11 -> Other | ... N11: =BUDGET_PLAN!J11 -> 1 | O11: =BUDGET_PLAN!Z11 -> 0 | P11: =BUDGET_PLAN!AC11 -> Medium | Q11: =BUDGET_PLAN!AD11 -> School Fees | R11: =BUDGET_PLAN!AE11 -> 0
A12: =SETUP!B17 -> 1.0 | B12: =SETUP!B6 -> Musanze | C12: =SETUP!B8 -> 2027 | D12: =SETUP!B9 -> Annual | E12: =BUDGET_PLAN!A12 -> BL-007 | F12: =BUDGET_PLAN!B12 -> OPERATING EXPENSES | G12: =BUDGET_PLAN!C12 -> Food Expenses | H12: =BUDGET_PLAN!D12 -> 0 | I12: =BUDGET_PLAN!E12 -> 0 | J12: =BUDGET_PLAN!F12 -> Monthly | K12: =BUDGET_PLAN!G12 -> 0 | L12: =BUDGET_PLAN!H12 -> Other | ... N12: =BUDGET_PLAN!J12 -> 1 | O12: =BUDGET_PLAN!Z12 -> 0 | P12: =BUDGET_PLAN!AC12 -> Medium | Q12: =BUDGET_PLAN!AD12 -> School Fees | R12: =BUDGET_PLAN!AE12 -> 0
A13: =SETUP!B17 -> 1.0 | B13: =SETUP!B6 -> Musanze | C13: =SETUP!B8 -> 2027 | D13: =SETUP!B9 -> Annual | E13: =BUDGET_PLAN!A13 -> BL-008 | F13: =BUDGET_PLAN!B13 -> OPERATING EXPENSES | G13: =BUDGET_PLAN!C13 -> Travel, Mission & Transport Expenses | H13: =BUDGET_PLAN!D13 -> 0 | I13: =BUDGET_PLAN!E13 -> 0 | J13: =BUDGET_PLAN!F13 -> Monthly | K13: =BUDGET_PLAN!G13 -> 0 | L13: =BUDGET_PLAN!H13 -> Other | ... N13: =BUDGET_PLAN!J13 -> 1 | O13: =BUDGET_PLAN!Z13 -> 0 | P13: =BUDGET_PLAN!AC13 -> Medium | Q13: =BUDGET_PLAN!AD13 -> School Fees | R13: =BUDGET_PLAN!AE13 -> 0
A14: =SETUP!B17 -> 1.0 | B14: =SETUP!B6 -> Musanze | C14: =SETUP!B8 -> 2027 | D14: =SETUP!B9 -> Annual | E14: =BUDGET_PLAN!A14 -> BL-009 | F14: =BUDGET_PLAN!B14 -> OPERATING EXPENSES | G14: =BUDGET_PLAN!C14 -> Fuel | H14: =BUDGET_PLAN!D14 -> 0 | I14: =BUDGET_PLAN!E14 -> 0 | J14: =BUDGET_PLAN!F14 -> Monthly | K14: =BUDGET_PLAN!G14 -> 0 | L14: =BUDGET_PLAN!H14 -> Other | ... N14: =BUDGET_PLAN!J14 -> 1 | O14: =BUDGET_PLAN!Z14 -> 0 | P14: =BUDGET_PLAN!AC14 -> Medium | Q14: =BUDGET_PLAN!AD14 -> School Fees | R14: =BUDGET_PLAN!AE14 -> 0
A15: =SETUP!B17 -> 1.0 | B15: =SETUP!B6 -> Musanze | C15: =SETUP!B8 -> 2027 | D15: =SETUP!B9 -> Annual | E15: =BUDGET_PLAN!A15 -> BL-010 | F15: =BUDGET_PLAN!B15 -> OPERATING EXPENSES | G15: =BUDGET_PLAN!C15 -> Vehicle Maintenance | H15: =BUDGET_PLAN!D15 -> 0 | I15: =BUDGET_PLAN!E15 -> 0 | J15: =BUDGET_PLAN!F15 -> Monthly | K15: =BUDGET_PLAN!G15 -> 0 | L15: =BUDGET_PLAN!H15 -> Other | ... N15: =BUDGET_PLAN!J15 -> 1 | O15: =BUDGET_PLAN!Z15 -> 0 | P15: =BUDGET_PLAN!AC15 -> Medium | Q15: =BUDGET_PLAN!AD15 -> School Fees | R15: =BUDGET_PLAN!AE15 -> 0
A16: =SETUP!B17 -> 1.0 | B16: =SETUP!B6 -> Musanze | C16: =SETUP!B8 -> 2027 | D16: =SETUP!B9 -> Annual | E16: =BUDGET_PLAN!A16 -> BL-011 | F16: =BUDGET_PLAN!B16 -> OPERATING EXPENSES | G16: =BUDGET_PLAN!C16 -> Utilities (Water & Electricity) | H16: =BUDGET_PLAN!D16 -> 0 | I16: =BUDGET_PLAN!E16 -> 0 | J16: =BUDGET_PLAN!F16 -> Monthly | K16: =BUDGET_PLAN!G16 -> 0 | L16: =BUDGET_PLAN!H16 -> Other | ... N16: =BUDGET_PLAN!J16 -> 1 | O16: =BUDGET_PLAN!Z16 -> 0 | P16: =BUDGET_PLAN!AC16 -> Medium | Q16: =BUDGET_PLAN!AD16 -> School Fees | R16: =BUDGET_PLAN!AE16 -> 0
A17: =SETUP!B17 -> 1.0 | B17: =SETUP!B6 -> Musanze | C17: =SETUP!B8 -> 2027 | D17: =SETUP!B9 -> Annual | E17: =BUDGET_PLAN!A17 -> BL-012 | F17: =BUDGET_PLAN!B17 -> OPERATING EXPENSES | G17: =BUDGET_PLAN!C17 -> Rental Expenses | H17: =BUDGET_PLAN!D17 -> 0 | I17: =BUDGET_PLAN!E17 -> 0 | J17: =BUDGET_PLAN!F17 -> Monthly | K17: =BUDGET_PLAN!G17 -> 0 | L17: =BUDGET_PLAN!H17 -> Other | ... N17: =BUDGET_PLAN!J17 -> 1 | O17: =BUDGET_PLAN!Z17 -> 0 | P17: =BUDGET_PLAN!AC17 -> Medium | Q17: =BUDGET_PLAN!AD17 -> School Fees | R17: =BUDGET_PLAN!AE17 -> 0
A18: =SETUP!B17 -> 1.0 | B18: =SETUP!B6 -> Musanze | C18: =SETUP!B8 -> 2027 | D18: =SETUP!B9 -> Annual | E18: =BUDGET_PLAN!A18 -> BL-013 | F18: =BUDGET_PLAN!B18 -> OPERATING EXPENSES | G18: =BUDGET_PLAN!C18 -> Insurance | H18: =BUDGET_PLAN!D18 -> 0 | I18: =BUDGET_PLAN!E18 -> 0 | J18: =BUDGET_PLAN!F18 -> Monthly | K18: =BUDGET_PLAN!G18 -> 0 | L18: =BUDGET_PLAN!H18 -> Other | ... N18: =BUDGET_PLAN!J18 -> 1 | O18: =BUDGET_PLAN!Z18 -> 0 | P18: =BUDGET_PLAN!AC18 -> Medium | Q18: =BUDGET_PLAN!AD18 -> School Fees | R18: =BUDGET_PLAN!AE18 -> 0
A19: =SETUP!B17 -> 1.0 | B19: =SETUP!B6 -> Musanze | C19: =SETUP!B8 -> 2027 | D19: =SETUP!B9 -> Annual | E19: =BUDGET_PLAN!A19 -> BL-014 | F19: =BUDGET_PLAN!B19 -> OPERATING EXPENSES | G19: =BUDGET_PLAN!C19 -> Taxes | H19: =BUDGET_PLAN!D19 -> 0 | I19: =BUDGET_PLAN!E19 -> 0 | J19: =BUDGET_PLAN!F19 -> Monthly | K19: =BUDGET_PLAN!G19 -> 0 | L19: =BUDGET_PLAN!H19 -> Other | ... N19: =BUDGET_PLAN!J19 -> 1 | O19: =BUDGET_PLAN!Z19 -> 0 | P19: =BUDGET_PLAN!AC19 -> Medium | Q19: =BUDGET_PLAN!AD19 -> School Fees | R19: =BUDGET_PLAN!AE19 -> 0
A20: =SETUP!B17 -> 1.0 | B20: =SETUP!B6 -> Musanze | C20: =SETUP!B8 -> 2027 | D20: =SETUP!B9 -> Annual | E20: =BUDGET_PLAN!A20 -> BL-015 | F20: =BUDGET_PLAN!B20 -> OPERATING EXPENSES | G20: =BUDGET_PLAN!C20 -> Communication | H20: =BUDGET_PLAN!D20 -> 0 | I20: =BUDGET_PLAN!E20 -> 0 | J20: =BUDGET_PLAN!F20 -> Monthly | K20: =BUDGET_PLAN!G20 -> 0 | L20: =BUDGET_PLAN!H20 -> Other | ... N20: =BUDGET_PLAN!J20 -> 1 | O20: =BUDGET_PLAN!Z20 -> 0 | P20: =BUDGET_PLAN!AC20 -> Medium | Q20: =BUDGET_PLAN!AD20 -> School Fees | R20: =BUDGET_PLAN!AE20 -> 0
A21: =SETUP!B17 -> 1.0 | B21: =SETUP!B6 -> Musanze | C21: =SETUP!B8 -> 2027 | D21: =SETUP!B9 -> Annual | E21: =BUDGET_PLAN!A21 -> BL-016 | F21: =BUDGET_PLAN!B21 -> OPERATING EXPENSES | G21: =BUDGET_PLAN!C21 -> Capacity Building | H21: =BUDGET_PLAN!D21 -> 0 | I21: =BUDGET_PLAN!E21 -> 0 | J21: =BUDGET_PLAN!F21 -> Monthly | K21: =BUDGET_PLAN!G21 -> 0 | L21: =BUDGET_PLAN!H21 -> Other | ... N21: =BUDGET_PLAN!J21 -> 1 | O21: =BUDGET_PLAN!Z21 -> 0 | P21: =BUDGET_PLAN!AC21 -> Medium | Q21: =BUDGET_PLAN!AD21 -> School Fees | R21: =BUDGET_PLAN!AE21 -> 0
A22: =SETUP!B17 -> 1.0 | B22: =SETUP!B6 -> Musanze | C22: =SETUP!B8 -> 2027 | D22: =SETUP!B9 -> Annual | E22: =BUDGET_PLAN!A22 -> BL-017 | F22: =BUDGET_PLAN!B22 -> OPERATING EXPENSES | G22: =BUDGET_PLAN!C22 -> Audit Fees | H22: =BUDGET_PLAN!D22 -> 0 | I22: =BUDGET_PLAN!E22 -> 0 | J22: =BUDGET_PLAN!F22 -> Monthly | K22: =BUDGET_PLAN!G22 -> 0 | L22: =BUDGET_PLAN!H22 -> Other | ... N22: =BUDGET_PLAN!J22 -> 1 | O22: =BUDGET_PLAN!Z22 -> 0 | P22: =BUDGET_PLAN!AC22 -> Medium | Q22: =BUDGET_PLAN!AD22 -> School Fees | R22: =BUDGET_PLAN!AE22 -> 0
A23: =SETUP!B17 -> 1.0 | B23: =SETUP!B6 -> Musanze | C23: =SETUP!B8 -> 2027 | D23: =SETUP!B9 -> Annual | E23: =BUDGET_PLAN!A23 -> BL-018 | F23: =BUDGET_PLAN!B23 -> OPERATING EXPENSES | G23: =BUDGET_PLAN!C23 -> Rehabilitation & Maintenance | H23: =BUDGET_PLAN!D23 -> 0 | I23: =BUDGET_PLAN!E23 -> 0 | J23: =BUDGET_PLAN!F23 -> Monthly | K23: =BUDGET_PLAN!G23 -> 0 | L23: =BUDGET_PLAN!H23 -> Other | ... N23: =BUDGET_PLAN!J23 -> 1 | O23: =BUDGET_PLAN!Z23 -> 0 | P23: =BUDGET_PLAN!AC23 -> Medium | Q23: =BUDGET_PLAN!AD23 -> School Fees | R23: =BUDGET_PLAN!AE23 -> 0
A24: =SETUP!B17 -> 1.0 | B24: =SETUP!B6 -> Musanze | C24: =SETUP!B8 -> 2027 | D24: =SETUP!B9 -> Annual | E24: =BUDGET_PLAN!A24 -> BL-019 | F24: =BUDGET_PLAN!B24 -> OPERATING EXPENSES | G24: =BUDGET_PLAN!C24 -> Donation | H24: =BUDGET_PLAN!D24 -> 0 | I24: =BUDGET_PLAN!E24 -> 0 | J24: =BUDGET_PLAN!F24 -> Monthly | K24: =BUDGET_PLAN!G24 -> 0 | L24: =BUDGET_PLAN!H24 -> Other | ... N24: =BUDGET_PLAN!J24 -> 1 | O24: =BUDGET_PLAN!Z24 -> 0 | P24: =BUDGET_PLAN!AC24 -> Medium | Q24: =BUDGET_PLAN!AD24 -> School Fees | R24: =BUDGET_PLAN!AE24 -> 0
A25: =SETUP!B17 -> 1.0 | B25: =SETUP!B6 -> Musanze | C25: =SETUP!B8 -> 2027 | D25: =SETUP!B9 -> Annual | E25: =BUDGET_PLAN!A25 -> BL-020 | F25: =BUDGET_PLAN!B25 -> OPERATING EXPENSES | G25: =BUDGET_PLAN!C25 -> First Aid & Hygiene | H25: =BUDGET_PLAN!D25 -> 0 | I25: =BUDGET_PLAN!E25 -> 0 | J25: =BUDGET_PLAN!F25 -> Monthly | K25: =BUDGET_PLAN!G25 -> 0 | L25: =BUDGET_PLAN!H25 -> Other | ... N25: =BUDGET_PLAN!J25 -> 1 | O25: =BUDGET_PLAN!Z25 -> 0 | P25: =BUDGET_PLAN!AC25 -> Medium | Q25: =BUDGET_PLAN!AD25 -> School Fees | R25: =BUDGET_PLAN!AE25 -> 0
A26: =SETUP!B17 -> 1.0 | B26: =SETUP!B6 -> Musanze | C26: =SETUP!B8 -> 2027 | D26: =SETUP!B9 -> Annual | E26: =BUDGET_PLAN!A26 -> BL-021 | F26: =BUDGET_PLAN!B26 -> OPERATING EXPENSES | G26: =BUDGET_PLAN!C26 -> Fines & Penalties | H26: =BUDGET_PLAN!D26 -> 0 | I26: =BUDGET_PLAN!E26 -> 0 | J26: =BUDGET_PLAN!F26 -> Monthly | K26: =BUDGET_PLAN!G26 -> 0 | L26: =BUDGET_PLAN!H26 -> Other | ... N26: =BUDGET_PLAN!J26 -> 1 | O26: =BUDGET_PLAN!Z26 -> 0 | P26: =BUDGET_PLAN!AC26 -> Medium | Q26: =BUDGET_PLAN!AD26 -> School Fees | R26: =BUDGET_PLAN!AE26 -> 0
A27: =SETUP!B17 -> 1.0 | B27: =SETUP!B6 -> Musanze | C27: =SETUP!B8 -> 2027 | D27: =SETUP!B9 -> Annual | E27: =BUDGET_PLAN!A27 -> BL-022 | F27: =BUDGET_PLAN!B27 -> OPERATING EXPENSES | G27: =BUDGET_PLAN!C27 -> Payables | H27: =BUDGET_PLAN!D27 -> 0 | I27: =BUDGET_PLAN!E27 -> 0 | J27: =BUDGET_PLAN!F27 -> Monthly | K27: =BUDGET_PLAN!G27 -> 0 | L27: =BUDGET_PLAN!H27 -> Other | ... N27: =BUDGET_PLAN!J27 -> 1 | O27: =BUDGET_PLAN!Z27 -> 0 | P27: =BUDGET_PLAN!AC27 -> Medium | Q27: =BUDGET_PLAN!AD27 -> School Fees | R27: =BUDGET_PLAN!AE27 -> 0
A28: =SETUP!B17 -> 1.0 | B28: =SETUP!B6 -> Musanze | C28: =SETUP!B8 -> 2027 | D28: =SETUP!B9 -> Annual | E28: =BUDGET_PLAN!A28 -> BL-023 | F28: =BUDGET_PLAN!B28 -> ADMINISTRATIVE COSTS | G28: =BUDGET_PLAN!C28 -> Staff Salaries | H28: =BUDGET_PLAN!D28 -> 0 | I28: =BUDGET_PLAN!E28 -> 0 | J28: =BUDGET_PLAN!F28 -> Monthly | K28: =BUDGET_PLAN!G28 -> 0 | L28: =BUDGET_PLAN!H28 -> Other | ... N28: =BUDGET_PLAN!J28 -> 1 | O28: =BUDGET_PLAN!Z28 -> 0 | P28: =BUDGET_PLAN!AC28 -> Medium | Q28: =BUDGET_PLAN!AD28 -> School Fees | R28: =BUDGET_PLAN!AE28 -> 0
A29: =SETUP!B17 -> 1.0 | B29: =SETUP!B6 -> Musanze | C29: =SETUP!B8 -> 2027 | D29: =SETUP!B9 -> Annual | E29: =BUDGET_PLAN!A29 -> BL-024 | F29: =BUDGET_PLAN!B29 -> ADMINISTRATIVE COSTS | G29: =BUDGET_PLAN!C29 -> RSSB Contributions | H29: =BUDGET_PLAN!D29 -> 0 | I29: =BUDGET_PLAN!E29 -> 0 | J29: =BUDGET_PLAN!F29 -> Monthly | K29: =BUDGET_PLAN!G29 -> 0 | L29: =BUDGET_PLAN!H29 -> Other | ... N29: =BUDGET_PLAN!J29 -> 1 | O29: =BUDGET_PLAN!Z29 -> 0 | P29: =BUDGET_PLAN!AC29 -> Medium | Q29: =BUDGET_PLAN!AD29 -> School Fees | R29: =BUDGET_PLAN!AE29 -> 0
A30: =SETUP!B17 -> 1.0 | B30: =SETUP!B6 -> Musanze | C30: =SETUP!B8 -> 2027 | D30: =SETUP!B9 -> Annual | E30: =BUDGET_PLAN!A30 -> BL-025 | F30: =BUDGET_PLAN!B30 -> ADMINISTRATIVE COSTS | G30: =BUDGET_PLAN!C30 -> Marketing, Meetings, Conferences & Rewards | H30: =BUDGET_PLAN!D30 -> 0 | I30: =BUDGET_PLAN!E30 -> 0 | J30: =BUDGET_PLAN!F30 -> Monthly | K30: =BUDGET_PLAN!G30 -> 0 | L30: =BUDGET_PLAN!H30 -> Other | ... N30: =BUDGET_PLAN!J30 -> 1 | O30: =BUDGET_PLAN!Z30 -> 0 | P30: =BUDGET_PLAN!AC30 -> Medium | Q30: =BUDGET_PLAN!AD30 -> School Fees | R30: =BUDGET_PLAN!AE30 -> 0
A31: =SETUP!B17 -> 1.0 | B31: =SETUP!B6 -> Musanze | C31: =SETUP!B8 -> 2027 | D31: =SETUP!B9 -> Annual | E31: =BUDGET_PLAN!A31 -> BL-026 | F31: =BUDGET_PLAN!B31 -> FINANCE COSTS | G31: =BUDGET_PLAN!C31 -> Bank Loan Payments | H31: =BUDGET_PLAN!D31 -> 0 | I31: =BUDGET_PLAN!E31 -> 0 | J31: =BUDGET_PLAN!F31 -> Monthly | K31: =BUDGET_PLAN!G31 -> 0 | L31: =BUDGET_PLAN!H31 -> Other | ... N31: =BUDGET_PLAN!J31 -> 1 | O31: =BUDGET_PLAN!Z31 -> 0 | P31: =BUDGET_PLAN!AC31 -> Medium | Q31: =BUDGET_PLAN!AD31 -> School Fees | R31: =BUDGET_PLAN!AE31 -> 0
A32: =SETUP!B17 -> 1.0 | B32: =SETUP!B6 -> Musanze | C32: =SETUP!B8 -> 2027 | D32: =SETUP!B9 -> Annual | E32: =BUDGET_PLAN!A32 -> BL-027 | F32: =BUDGET_PLAN!B32 -> FINANCE COSTS | G32: =BUDGET_PLAN!C32 -> Bank Charges & Account Maintenance Fees | H32: =BUDGET_PLAN!D32 -> 0 | I32: =BUDGET_PLAN!E32 -> 0 | J32: =BUDGET_PLAN!F32 -> Monthly | K32: =BUDGET_PLAN!G32 -> 0 | L32: =BUDGET_PLAN!H32 -> Other | ... N32: =BUDGET_PLAN!J32 -> 1 | O32: =BUDGET_PLAN!Z32 -> 0 | P32: =BUDGET_PLAN!AC32 -> Medium | Q32: =BUDGET_PLAN!AD32 -> School Fees | R32: =BUDGET_PLAN!AE32 -> 0

Sheet LISTS
A1: Branches | B1: Budget Years | C1: Budget Periods | D1: Currencies | E1: Calculation Modes | F1: Priorities | G1: Funding Sources | H1: Statuses | I1: Units | J1: Request Statuses | K1: Sections | L1: Line Types | M1: Headteacher Approval Mode
A2: Musanze | B2: 2026 | C2: Annual | D2: RWF | E2: Monthly | F2: Critical | G2: School Fees | H2: Draft | I2: Student | J2: Draft | K2: INCOME | L2: Operating Income | M2: System Approval
A3: Nyabihu | B3: 2027 | C3: Term 1 | D3: USD | E3: Unit-based | F3: High | G3: Government Grant | H3: Submitted | I3: Meal | J3: Submitted | K3: OPERATING EXPENSES | L3: Operating Expense | M3: Evidence-only Approval
A4: Rubavu | B4: 2028 | C4: Term 2 | D4: EUR | E4: Manual Annual | F4: Medium | G4: Donation | H4: Returned | I4: Trip | J4: Procurement Approved | K4: ADMINISTRATIVE COSTS | L4: Administrative Expense
A5: Runda | B5: 2029 | C5: Term 3 | F5: Low | G5: Loan | H5: Approved | I5: Litre | J5: Budget Approved | K5: FINANCE COSTS | L5: Finance Cost
A6: Nyamasheke | B6: 2030 | C6: Monthly | G6: Other | H6: Rejected | I6: Month | J6: Finance Authorized
A7: Rubengera | C7: Quarterly | H7: Superseded | I7: Term | J7: Partially Paid
A8: Fumbwe | I8: Item | J8: Paid
A9: Kayonza | I9: Package | J9: Receipt Confirmed
A10: Kiramuruzi | I10: Service | J10: Closed
A11: Muyumbu | I11: Employee | J11: Returned
A12: Susa | I12: Vehicle | J12: Rejected
A13: Kanzenze | I13: Building | J13: Cancelled
A14: Burera | I14: Other
A15: Ngororero
A16: Kabarore
