Workbook

Sheet Dashboard
A1: SECONDARY SCHOOL BUDGET DASHBOARD
A4: Total Budget | B4: ='Budget Summary'!B38 -> 0
A5: Total Actual | B5: ='Budget Summary'!C38 -> 0
A6: Budget Variance | B6: ='Budget Summary'!D38 -> 0
A7: Variance % | B7: ='Budget Summary'!E38 -> 0
A8: Total Fee Revenue | B8: ='Fees & Enrollment'!J14 -> 0
A9: Expected Students | B9: ='Fees & Enrollment'!B14 -> 0
A12: Key Instructions
A13: • Enter expected students and fee rates in Fees & Enrollment.
A14: • Enter detailed quantities and unit costs in Detailed Budget.
A15: • Record actual transactions in Actuals.
A16: • Budget Summary calculates annual budget, actuals and variances automatically.
A17: • Use Monthly Cash Flow to plan liquidity and monthly spending.

Sheet Budget Summary
A1: SECONDARY SCHOOL ANNUAL BUDGET TEMPLATE
A3: School Name | B3: Enter school name
A4: Academic Year | B4: 2026
A5: Currency | B5: RWF
A7: Category | B7: Annual Budget | C7: Annual Actual | D7: Variance | E7: Variance % | F7: Monthly Budget | G7: Monthly Actual | H7: Status
A8: School Fees / Tuition | D8: =B8-C8 -> 0 | E8: =IFERROR(D8/B8,0) -> 0 | F8: =B8/12 -> 0 | G8: =C8/12 -> 0 | H8: =IF(D8>=0,"Within/Under Budget","Over Budget") -> Within/Under Budget
A9: Boarding Fees | D9: =B9-C9 -> 0 | E9: =IFERROR(D9/B9,0) -> 0 | F9: =B9/12 -> 0 | G9: =C9/12 -> 0 | H9: =IF(D9>=0,"Within/Under Budget","Over Budget") -> Within/Under Budget
A10: Registration / Admission Fees | D10: =B10-C10 -> 0 | E10: =IFERROR(D10/B10,0) -> 0 | F10: =B10/12 -> 0 | G10: =C10/12 -> 0 | H10: =IF(D10>=0,"Within/Under Budget","Over Budget") -> Within/Under Budget
A11: Examination Fees | D11: =B11-C11 -> 0 | E11: =IFERROR(D11/B11,0) -> 0 | F11: =B11/12 -> 0 | G11: =C11/12 -> 0 | H11: =IF(D11>=0,"Within/Under Budget","Over Budget") -> Within/Under Budget
A12: Transport Fees | D12: =B12-C12 -> 0 | E12: =IFERROR(D12/B12,0) -> 0 | F12: =B12/12 -> 0 | G12: =C12/12 -> 0 | H12: =IF(D12>=0,"Within/Under Budget","Over Budget") -> Within/Under Budget
A13: Other Student Fees | D13: =B13-C13 -> 0 | E13: =IFERROR(D13/B13,0) -> 0 | F13: =B13/12 -> 0 | G13: =C13/12 -> 0 | H13: =IF(D13>=0,"Within/Under Budget","Over Budget") -> Within/Under Budget
A14: Government / Grant Income | D14: =B14-C14 -> 0 | E14: =IFERROR(D14/B14,0) -> 0 | F14: =B14/12 -> 0 | G14: =C14/12 -> 0 | H14: =IF(D14>=0,"Within/Under Budget","Over Budget") -> Within/Under Budget
A15: Donations / Fundraising | D15: =B15-C15 -> 0 | E15: =IFERROR(D15/B15,0) -> 0 | F15: =B15/12 -> 0 | G15: =C15/12 -> 0 | H15: =IF(D15>=0,"Within/Under Budget","Over Budget") -> Within/Under Budget
A16: Other Income | D16: =B16-C16 -> 0 | E16: =IFERROR(D16/B16,0) -> 0 | F16: =B16/12 -> 0 | G16: =C16/12 -> 0 | H16: =IF(D16>=0,"Within/Under Budget","Over Budget") -> Within/Under Budget
A17: Teaching & Learning Materials | D17: =B17-C17 -> 0 | E17: =IFERROR(D17/B17,0) -> 0 | F17: =B17/12 -> 0 | G17: =C17/12 -> 0 | H17: =IF(D17>=0,"Within/Under Budget","Over Budget") -> Within/Under Budget
A18: Books & Library | D18: =B18-C18 -> 0 | E18: =IFERROR(D18/B18,0) -> 0 | F18: =B18/12 -> 0 | G18: =C18/12 -> 0 | H18: =IF(D18>=0,"Within/Under Budget","Over Budget") -> Within/Under Budget
A19: Laboratory Supplies | D19: =B19-C19 -> 0 | E19: =IFERROR(D19/B19,0) -> 0 | F19: =B19/12 -> 0 | G19: =C19/12 -> 0 | H19: =IF(D19>=0,"Within/Under Budget","Over Budget") -> Within/Under Budget
A20: ICT / Computer Costs | D20: =B20-C20 -> 0 | E20: =IFERROR(D20/B20,0) -> 0 | F20: =B20/12 -> 0 | G20: =C20/12 -> 0 | H20: =IF(D20>=0,"Within/Under Budget","Over Budget") -> Within/Under Budget
A21: Teachers' Salaries & Benefits | B21: =SUMIF('Detailed Budget'!$B$8:$B$100,"Teachers' Salaries & Benefits",'Detailed Budget'!$F$8:$F$100) -> 0 | C21: =SUMIF(Actuals!$B$8:$B$100,"Teachers' Salaries & Benefits",Actuals!$F$8:$F$100) -> 0 | D21: =B21-C21 -> 0 | E21: =IFERROR(D21/B21,0) -> 0 | F21: =B21/12 -> 0 | G21: =C21/12 -> 0 | H21: =IF(D21>=0,"Within/Under Budget","Over Budget") -> Within/Under Budget
A22: Administrative Staff Salaries | D22: =B22-C22 -> 0 | E22: =IFERROR(D22/B22,0) -> 0 | F22: =B22/12 -> 0 | G22: =C22/12 -> 0 | H22: =IF(D22>=0,"Within/Under Budget","Over Budget") -> Within/Under Budget
A23: Staff Training | D23: =B23-C23 -> 0 | E23: =IFERROR(D23/B23,0) -> 0 | F23: =B23/12 -> 0 | G23: =C23/12 -> 0 | H23: =IF(D23>=0,"Within/Under Budget","Over Budget") -> Within/Under Budget
A24: Food & Boarding | D24: =B24-C24 -> 0 | E24: =IFERROR(D24/B24,0) -> 0 | F24: =B24/12 -> 0 | G24: =C24/12 -> 0 | H24: =IF(D24>=0,"Within/Under Budget","Over Budget") -> Within/Under Budget
A25: Student Activities & Sports | D25: =B25-C25 -> 0 | E25: =IFERROR(D25/B25,0) -> 0 | F25: =B25/12 -> 0 | G25: =C25/12 -> 0 | H25: =IF(D25>=0,"Within/Under Budget","Over Budget") -> Within/Under Budget
A26: Medical / First Aid | D26: =B26-C26 -> 0 | E26: =IFERROR(D26/B26,0) -> 0 | F26: =B26/12 -> 0 | G26: =C26/12 -> 0 | H26: =IF(D26>=0,"Within/Under Budget","Over Budget") -> Within/Under Budget
A27: Utilities – Electricity | D27: =B27-C27 -> 0 | E27: =IFERROR(D27/B27,0) -> 0 | F27: =B27/12 -> 0 | G27: =C27/12 -> 0 | H27: =IF(D27>=0,"Within/Under Budget","Over Budget") -> Within/Under Budget
A28: Utilities – Water | D28: =B28-C28 -> 0 | E28: =IFERROR(D28/B28,0) -> 0 | F28: =B28/12 -> 0 | G28: =C28/12 -> 0 | H28: =IF(D28>=0,"Within/Under Budget","Over Budget") -> Within/Under Budget
A29: Internet & Communication | D29: =B29-C29 -> 0 | E29: =IFERROR(D29/B29,0) -> 0 | F29: =B29/12 -> 0 | G29: =C29/12 -> 0 | H29: =IF(D29>=0,"Within/Under Budget","Over Budget") -> Within/Under Budget
A30: Repairs & Maintenance | D30: =B30-C30 -> 0 | E30: =IFERROR(D30/B30,0) -> 0 | F30: =B30/12 -> 0 | G30: =C30/12 -> 0 | H30: =IF(D30>=0,"Within/Under Budget","Over Budget") -> Within/Under Budget
A31: Security | D31: =B31-C31 -> 0 | E31: =IFERROR(D31/B31,0) -> 0 | F31: =B31/12 -> 0 | G31: =C31/12 -> 0 | H31: =IF(D31>=0,"Within/Under Budget","Over Budget") -> Within/Under Budget
A32: Cleaning & Sanitation | D32: =B32-C32 -> 0 | E32: =IFERROR(D32/B32,0) -> 0 | F32: =B32/12 -> 0 | G32: =C32/12 -> 0 | H32: =IF(D32>=0,"Within/Under Budget","Over Budget") -> Within/Under Budget
A33: Transport / Fuel | D33: =B33-C33 -> 0 | E33: =IFERROR(D33/B33,0) -> 0 | F33: =B33/12 -> 0 | G33: =C33/12 -> 0 | H33: =IF(D33>=0,"Within/Under Budget","Over Budget") -> Within/Under Budget
... A37: Capital Expenditure | D37: =B37-C37 -> 0 | E37: =IFERROR(D37/B37,0) -> 0 | F37: =B37/12 -> 0 | G37: =C37/12 -> 0 | H37: =IF(D37>=0,"Within/Under Budget","Over Budget") -> Within/Under Budget
A38: TOTAL | B38: =SUM(B8:B37) -> 0 | C38: =SUM(C8:C37) -> 0 | D38: =SUM(D8:D37) -> 0 | E38: =IFERROR(D38/B38,0) -> 0 | F38: =SUM(F8:F37) -> 0 | G38: =SUM(G8:G37) -> 0 | H38: =IF(D38>=0,"Within/Under Budget","Over Budget") -> Within/Under Budget

Sheet Detailed Budget
A1: DETAILED ANNUAL BUDGET
A7: Budget Line / Description | B7: Category | C7: Type | D7: Quantity | E7: Unit Cost | F7: Annual Budget | G7: Notes
A8: School Fees / Tuition | B8: School Fees / Tuition | C8: Revenue | D8: 1 | E8: 0 | F8: =D8*E8 -> 0
A9: Boarding Fees | B9: Boarding Fees | C9: Revenue | D9: 1 | E9: 0 | F9: =D9*E9 -> 0
A10: Registration / Admission Fees | B10: Registration / Admission Fees | C10: Revenue | D10: 1 | E10: 0 | F10: =D10*E10 -> 0
A11: Examination Fees | B11: Examination Fees | C11: Revenue | D11: 1 | E11: 0 | F11: =D11*E11 -> 0
A12: Transport Fees | B12: Transport Fees | C12: Revenue | D12: 1 | E12: 0 | F12: =D12*E12 -> 0
A13: Other Student Fees | B13: Other Student Fees | C13: Revenue | D13: 1 | E13: 0 | F13: =D13*E13 -> 0
A14: Government / Grant Income | B14: Government / Grant Income | C14: Revenue | D14: 1 | E14: 0 | F14: =D14*E14 -> 0
A15: Donations / Fundraising | B15: Donations / Fundraising | C15: Revenue | D15: 1 | E15: 0 | F15: =D15*E15 -> 0
A16: Other Income | B16: Other Income | C16: Revenue | D16: 1 | E16: 0 | F16: =D16*E16 -> 0
A17: Teaching & Learning Materials | B17: Teaching & Learning Materials | C17: Expense | D17: 1 | E17: 0 | F17: =D17*E17 -> 0
A18: Books & Library | B18: Books & Library | C18: Expense | D18: 1 | E18: 0 | F18: =D18*E18 -> 0
A19: Laboratory Supplies | B19: Laboratory Supplies | C19: Expense | D19: 1 | E19: 0 | F19: =D19*E19 -> 0
... A37: Capital Expenditure | B37: Capital Expenditure | C37: Expense | D37: 1 | E37: 0 | F37: =D37*E37 -> 0
F38: =D38*E38 -> 0
F39: =D39*E39 -> 0
F40: =D40*E40 -> 0
F41: =D41*E41 -> 0
F42: =D42*E42 -> 0
F43: =D43*E43 -> 0
F44: =D44*E44 -> 0
F45: =D45*E45 -> 0
F46: =D46*E46 -> 0
F47: =D47*E47 -> 0
F48: =D48*E48 -> 0
F49: =D49*E49 -> 0
... F100: =D100*E100 -> 0

Sheet Fees & Enrollment
A1: STUDENT ENROLMENT & SCHOOL FEES BUDGET
A7: Grade / Class | B7: Expected Students | C7: Tuition / Term | D7: Terms | E7: Tuition Revenue | F7: Boarding Fee / Term | G7: Boarding Students | H7: Boarding Revenue | I7: Other Fee / Student | J7: Total Revenue
A8: S1 | B8: 0 | C8: 0 | D8: 3 | E8: =B8*C8*D8 -> 0 | F8: 0 | G8: 0 | H8: =F8*G8*D8 -> 0 | I8: 0 | J8: =E8+H8+(B8*I8) -> 0
A9: S2 | B9: 0 | C9: 0 | D9: 3 | E9: =B9*C9*D9 -> 0 | F9: 0 | G9: 0 | H9: =F9*G9*D9 -> 0 | I9: 0 | J9: =E9+H9+(B9*I9) -> 0
A10: S3 | B10: 0 | C10: 0 | D10: 3 | E10: =B10*C10*D10 -> 0 | F10: 0 | G10: 0 | H10: =F10*G10*D10 -> 0 | I10: 0 | J10: =E10+H10+(B10*I10) -> 0
A11: S4 | B11: 0 | C11: 0 | D11: 3 | E11: =B11*C11*D11 -> 0 | F11: 0 | G11: 0 | H11: =F11*G11*D11 -> 0 | I11: 0 | J11: =E11+H11+(B11*I11) -> 0
A12: S5 | B12: 0 | C12: 0 | D12: 3 | E12: =B12*C12*D12 -> 0 | F12: 0 | G12: 0 | H12: =F12*G12*D12 -> 0 | I12: 0 | J12: =E12+H12+(B12*I12) -> 0
A13: S6 | B13: 0 | C13: 0 | D13: 3 | E13: =B13*C13*D13 -> 0 | F13: 0 | G13: 0 | H13: =F13*G13*D13 -> 0 | I13: 0 | J13: =E13+H13+(B13*I13) -> 0
A14: TOTAL | B14: =SUM(B8:B13) -> 0 | E14: =SUM(E8:E13) -> 0 | H14: =SUM(H8:H13) -> 0 | J14: =SUM(J8:J13) -> 0

Sheet Actuals
A1: ACTUAL EXPENDITURE / REVENUE TRACKER
A7: Date | B7: Category | C7: Description | D7: Type | E7: Reference | F7: Amount | G7: Notes
F8: 0
F9: 0
F10: 0
F11: 0
F12: 0
F13: 0
F14: 0
F15: 0
F16: 0
F17: 0
F18: 0
F19: 0
... F100: 0

Sheet Monthly Cash Flow
A1: MONTHLY CASH FLOW BUDGET
A7: Cash Flow Item | B7: Jan | C7: Feb | D7: Mar | E7: Apr | F7: May | G7: Jun | H7: Jul | I7: Aug | J7: Sep | K7: Oct | L7: Nov | M7: Dec | N7: Annual Total
A8: Opening Cash Balance | C8: =B23 -> 0 | D8: =C23 -> 0 | E8: =D23 -> 0 | F8: =E23 -> 0 | G8: =F23 -> 0 | H8: =G23 -> 0 | I8: =H23 -> 0 | J8: =I23 -> 0 | ... M8: =L23 -> 0 | N8: =M8 -> 0
A9: School Fees / Tuition Receipts | N9: =SUM(B9:M9) -> 0
A10: Other Receipts | N10: =SUM(B10:M10) -> 0
A11: Total Cash Inflows | B11: =SUM(B9:B10) -> 0 | C11: =SUM(C9:C10) -> 0 | D11: =SUM(D9:D10) -> 0 | E11: =SUM(E9:E10) -> 0 | F11: =SUM(F9:F10) -> 0 | G11: =SUM(G9:G10) -> 0 | H11: =SUM(H9:H10) -> 0 | I11: =SUM(I9:I10) -> 0 | ... M11: =SUM(M9:M10) -> 0 | N11: =SUM(B11:M11) -> 0
A13: Salaries & Benefits | N13: =SUM(B13:M13) -> 0
A14: Teaching & Learning | N14: =SUM(B14:M14) -> 0
A15: Food & Boarding | N15: =SUM(B15:M15) -> 0
A16: Utilities | N16: =SUM(B16:M16) -> 0
A17: Repairs & Maintenance | N17: =SUM(B17:M17) -> 0
A18: Other Operating Costs | N18: =SUM(B18:M18) -> 0
A19: Capital Expenditure | N19: =SUM(B19:M19) -> 0
A20: Total Cash Outflows | B20: =SUM(B13:B19) -> 0 | C20: =SUM(C13:C19) -> 0 | D20: =SUM(D13:D19) -> 0 | E20: =SUM(E13:E19) -> 0 | F20: =SUM(F13:F19) -> 0 | G20: =SUM(G13:G19) -> 0 | H20: =SUM(H13:H19) -> 0 | I20: =SUM(I13:I19) -> 0 | ... M20: =SUM(M13:M19) -> 0 | N20: =SUM(B20:M20) -> 0
A22: Net Cash Flow | B22: =B11-B20 -> 0 | C22: =C11-C20 -> 0 | D22: =D11-D20 -> 0 | E22: =E11-E20 -> 0 | F22: =F11-F20 -> 0 | G22: =G11-G20 -> 0 | H22: =H11-H20 -> 0 | I22: =I11-I20 -> 0 | ... M22: =M11-M20 -> 0 | N22: =SUM(B22:M22) -> 0
A23: Closing Cash Balance | B23: =B8+B22 -> 0 | C23: =C8+C22 -> 0 | D23: =D8+D22 -> 0 | E23: =E8+E22 -> 0 | F23: =F8+F22 -> 0 | G23: =G8+G22 -> 0 | H23: =H8+H22 -> 0 | I23: =I8+I22 -> 0 | ... M23: =M8+M22 -> 0 | N23: =M23 -> 0
